dash_antd/Alert.py
dash_antd/AutoComplete.py
dash_antd/Button.py
dash_antd/Card.py
dash_antd/CheckableTag.py
dash_antd/Checkbox.py
dash_antd/CheckboxGroup.py
dash_antd/Col.py
dash_antd/ConfigProvider.py
dash_antd/Content.py
dash_antd/DatePicker.py
dash_antd/DateRangePicker.py
dash_antd/Divider.py
dash_antd/DropdownButton.py
dash_antd/DropdownMenu.py
dash_antd/Footer.py
dash_antd/Header.py
dash_antd/Icon.py
dash_antd/Input.py
dash_antd/InputNumber.py
dash_antd/Layout.py
dash_antd/Menu.py
dash_antd/MenuItem.py
dash_antd/Page.py
dash_antd/PagesWithSidebar.py
dash_antd/Radio.py
dash_antd/RadioButton.py
dash_antd/RadioGroup.py
dash_antd/Row.py
dash_antd/Segmented.py
dash_antd/Select.py
dash_antd/Sidebar.py
dash_antd/Slider.py
dash_antd/Space.py
dash_antd/Steps.py
dash_antd/Switch.py
dash_antd/TabPane.py
dash_antd/Tabs.py
dash_antd/Tag.py
dash_antd/TextArea.py
dash_antd/TimePicker.py
dash_antd/TimeRangePicker.py
dash_antd/Timeline.py
dash_antd/TimelineItem.py
dash_antd/__init__.py
dash_antd/_imports_.py
dash_antd/dash_antd.min.js
dash_antd/ext/__init__.py
dash_antd/ext/_sidebar.py
dash_antd/ext/_theming.py
dash_antd/metadata.json
dash_antd/package.json
dash_antd/py.typed
dash_antd-0.1.6.dist-info/METADATA
dash_antd-0.1.6.dist-info/WHEEL
dash_antd-0.1.6.dist-info/LICENSE
dash_antd-0.1.6.dist-info/RECORD
