Metadata-Version: 2.1
Name: dash-antd
Version: 0.1.6
Summary: Ant Design components for Plotly Dash
Home-page: https://github.com/roeap/dash-ant-design-components
License: MIT
Author: Robert Pack
Author-email: robstar.pack@gmail.com
Requires-Python: >=3.8,<4.0
Classifier: License :: OSI Approved :: MIT License
Classifier: Programming Language :: Python :: 3
Classifier: Programming Language :: Python :: 3.8
Classifier: Programming Language :: Python :: 3.9
Classifier: Programming Language :: Python :: 3.10
Classifier: Programming Language :: Python :: 3.11
Requires-Dist: dash (>=2.7,<3.0)
Project-URL: Repository, https://github.com/roeap/dash-ant-design-components
